Metadata-Version: 1.1
Name: bitstampy
Version: 0.0.7
Summary: Bitstamp API wrapper for Python
Home-page: https://github.com/unwitting/bitstampy
Author: https://github.com/unwitting
Author-email: jackprestonuk@gmail.com
License: LICENSE.txt
Platform: UNKNOWN
Classifier: Development Status :: 3 - Alpha
Classifier: Intended Audience :: Developers
Classifier: License :: OSI Approved :: MIT License
Classifier: Natural Language :: English
Classifier: Operating System :: OS Independent
Classifier: Programming Language :: Python :: 2
Classifier: Topic :: Internet :: WWW/HTTP
